
<annotation>
    <folder>data/train</folder>
    <filename>254242.jpeg</filename>
    <path>data/train/254242.jpeg</path>
    <source>
        <database>Unknown</database>
    </source>
    <size>
        <width>640</width>
        <height>480</height>
        <depth>3</depth>
    </size>
    <segmented>0</segmented>
        <object>
            <name>Airplane</name>
            <pose>Unspecified</pose>
            <truncated>0</truncated>
            <difficult>0</difficult>
            <bndbox>
                <xmin>40</xmin>
                <ymin>148</ymin>
                <xmax>573</xmax>
                <ymax>349</ymax>
            </bndbox>
        </object>
</annotation>
