
<annotation>
    <folder>data/train</folder>
    <filename>349804.jpeg</filename>
    <path>data/train/349804.jpeg</path>
    <source>
        <database>Unknown</database>
    </source>
    <size>
        <width>640</width>
        <height>424</height>
        <depth>3</depth>
    </size>
    <segmented>0</segmented>
        <object>
            <name>Airplane</name>
            <pose>Unspecified</pose>
            <truncated>0</truncated>
            <difficult>0</difficult>
            <bndbox>
                <xmin>344</xmin>
                <ymin>168</ymin>
                <xmax>590</xmax>
                <ymax>313</ymax>
            </bndbox>
        </object>
        <object>
            <name>Airplane</name>
            <pose>Unspecified</pose>
            <truncated>0</truncated>
            <difficult>0</difficult>
            <bndbox>
                <xmin>34</xmin>
                <ymin>175</ymin>
                <xmax>190</xmax>
                <ymax>287</ymax>
            </bndbox>
        </object>
        <object>
            <name>Airplane</name>
            <pose>Unspecified</pose>
            <truncated>0</truncated>
            <difficult>0</difficult>
            <bndbox>
                <xmin>289</xmin>
                <ymin>66</ymin>
                <xmax>559</xmax>
                <ymax>237</ymax>
            </bndbox>
        </object>
</annotation>
