
<annotation>
    <folder>data/train</folder>
    <filename>84521.jpeg</filename>
    <path>data/train/84521.jpeg</path>
    <source>
        <database>Unknown</database>
    </source>
    <size>
        <width>640</width>
        <height>426</height>
        <depth>3</depth>
    </size>
    <segmented>0</segmented>
        <object>
            <name>Train</name>
            <pose>Unspecified</pose>
            <truncated>0</truncated>
            <difficult>0</difficult>
            <bndbox>
                <xmin>1</xmin>
                <ymin>2</ymin>
                <xmax>638</xmax>
                <ymax>356</ymax>
            </bndbox>
        </object>
        <object>
            <name>Train</name>
            <pose>Unspecified</pose>
            <truncated>0</truncated>
            <difficult>0</difficult>
            <bndbox>
                <xmin>1</xmin>
                <ymin>2</ymin>
                <xmax>638</xmax>
                <ymax>356</ymax>
            </bndbox>
        </object>
</annotation>
